hermes_rheo/__init__.py
hermes_rheo/file_readers/__init__.py
hermes_rheo/file_readers/trios_rheo_txt.py
hermes_rheo/transforms/__init__.py
hermes_rheo/transforms/automated_mastercurve.py
hermes_rheo/transforms/mutation_number.py
hermes_rheo/transforms/owchirp_generation.py
hermes_rheo/transforms/rheo_analysis.py
hermes_rheo/transforms/states_to_conditions.py
hermes_rheo-1.2.11.dist-info/licenses/LICENSE
hermes_rheo-1.2.11.dist-info/METADATA
hermes_rheo-1.2.11.dist-info/WHEEL
hermes_rheo-1.2.11.dist-info/top_level.txt
hermes_rheo-1.2.11.dist-info/RECORD
